odoo/addons/analytic_activity_based_cost/README.rst
odoo/addons/analytic_activity_based_cost/__init__.py
odoo/addons/analytic_activity_based_cost/__manifest__.py
odoo/addons/analytic_activity_based_cost/demo/product_demo.xml
odoo/addons/analytic_activity_based_cost/i18n/analytic_activity_based_cost.pot
odoo/addons/analytic_activity_based_cost/i18n/es.po
odoo/addons/analytic_activity_based_cost/i18n/fr.po
odoo/addons/analytic_activity_based_cost/i18n/fr_FR.po
odoo/addons/analytic_activity_based_cost/i18n/it.po
odoo/addons/analytic_activity_based_cost/models/__init__.py
odoo/addons/analytic_activity_based_cost/models/account_analytic_line.py
odoo/addons/analytic_activity_based_cost/models/activity_cost_rule.py
odoo/addons/analytic_activity_based_cost/models/product.py
odoo/addons/analytic_activity_based_cost/readme/CONFIGURATION.rst
odoo/addons/analytic_activity_based_cost/readme/CONTRIBUTORS.rst
odoo/addons/analytic_activity_based_cost/readme/DESCRIPTION.rst
odoo/addons/analytic_activity_based_cost/readme/USAGE.rst
odoo/addons/analytic_activity_based_cost/security/ir.model.access.csv
odoo/addons/analytic_activity_based_cost/static/description/icon.png
odoo/addons/analytic_activity_based_cost/static/description/index.html
odoo/addons/analytic_activity_based_cost/views/account_analytic_line.xml
odoo/addons/analytic_activity_based_cost/views/activity_cost_rule_views.xml
odoo/addons/analytic_activity_based_cost/views/product.xml
odoo14_addon_analytic_activity_based_cost-14.0.4.1.0.dist-info/METADATA
odoo14_addon_analytic_activity_based_cost-14.0.4.1.0.dist-info/WHEEL
odoo14_addon_analytic_activity_based_cost-14.0.4.1.0.dist-info/top_level.txt
odoo14_addon_analytic_activity_based_cost-14.0.4.1.0.dist-info/RECORD
